{
  "coord": {
    "lon": 2.3488,
    "lat": 48.8534
  },
  "weather": [
    {
      "id": 804,
      "main": "Clouds",
      "description": "overcast clouds",
      "icon": "04n"
    }
  ],
  "base": "stations",
  "main": {
    "temp": 0.04,
    "feels_like": -5.48,
    "temp_min": -0.9,
    "temp_max": 1.16,
    "pressure": 1021,
    "humidity": 74,
    "sea_level": 1021,
    "grnd_level": 1011
  },
  "visibility": 10000,
  "wind": {
    "speed": 6.17,
    "deg": 50
  },
  "clouds": {
    "all": 100
  },
  "dt": 1766643984,
  "sys": {
    "type": 2,
    "id": 2012208,
    "country": "FR",
    "sunrise": 1766648582,
    "sunset": 1766678293
  },
  "timezone": 3600,
  "id": 2988507,
  "name": "Paris",
  "cod": 200,
  "_last_updated_utc": "2025-12-25T06:39:20.268Z"
}