{
  "coord": {
    "lon": 2.3488,
    "lat": 48.8534
  },
  "weather": [
    {
      "id": 804,
      "main": "Clouds",
      "description": "overcast clouds",
      "icon": "04d"
    }
  ],
  "base": "stations",
  "main": {
    "temp": 11.47,
    "feels_like": 10.87,
    "temp_min": 10.59,
    "temp_max": 12.43,
    "pressure": 994,
    "humidity": 84,
    "sea_level": 994,
    "grnd_level": 984
  },
  "visibility": 10000,
  "wind": {
    "speed": 6.17,
    "deg": 220
  },
  "clouds": {
    "all": 100
  },
  "dt": 1770396533,
  "sys": {
    "type": 2,
    "id": 2012208,
    "country": "FR",
    "sunrise": 1770362035,
    "sunset": 1770396927
  },
  "timezone": 3600,
  "id": 2988507,
  "name": "Paris",
  "cod": 200,
  "_last_updated_utc": "2026-02-06T16:53:31.692Z"
}