{
  "coord": {
    "lon": 2.3488,
    "lat": 48.8534
  },
  "weather": [
    {
      "id": 803,
      "main": "Clouds",
      "description": "broken clouds",
      "icon": "04d"
    }
  ],
  "base": "stations",
  "main": {
    "temp": 5.9,
    "feels_like": 0.84,
    "temp_min": 5.43,
    "temp_max": 6.28,
    "pressure": 996,
    "humidity": 85,
    "sea_level": 996,
    "grnd_level": 987
  },
  "visibility": 10000,
  "wind": {
    "speed": 9.77,
    "deg": 280
  },
  "clouds": {
    "all": 75
  },
  "dt": 1767968746,
  "sys": {
    "type": 2,
    "id": 2012208,
    "country": "FR",
    "sunrise": 1767944530,
    "sunset": 1767975162
  },
  "timezone": 3600,
  "id": 2988507,
  "name": "Paris",
  "cod": 200,
  "_last_updated_utc": "2026-01-09T14:29:10.226Z"
}