{
  "coord": {
    "lon": 2.3488,
    "lat": 48.8534
  },
  "weather": [
    {
      "id": 804,
      "main": "Clouds",
      "description": "overcast clouds",
      "icon": "04d"
    }
  ],
  "base": "stations",
  "main": {
    "temp": 18.81,
    "feels_like": 18.31,
    "temp_min": 18.41,
    "temp_max": 19.56,
    "pressure": 1012,
    "humidity": 60,
    "sea_level": 1012,
    "grnd_level": 1002
  },
  "visibility": 10000,
  "wind": {
    "speed": 5.76,
    "deg": 229,
    "gust": 10.11
  },
  "clouds": {
    "all": 95
  },
  "dt": 1780484539,
  "sys": {
    "type": 2,
    "id": 2012208,
    "country": "FR",
    "sunrise": 1780458641,
    "sunset": 1780516027
  },
  "timezone": 7200,
  "id": 2988507,
  "name": "Paris",
  "cod": 200,
  "_last_updated_utc": "2026-06-03T11:07:52.036Z"
}