{
  "coord": {
    "lon": 2.3488,
    "lat": 48.8534
  },
  "weather": [
    {
      "id": 800,
      "main": "Clear",
      "description": "clear sky",
      "icon": "01n"
    }
  ],
  "base": "stations",
  "main": {
    "temp": 1.08,
    "feels_like": -1.27,
    "temp_min": 0.28,
    "temp_max": 1.88,
    "pressure": 1019,
    "humidity": 78,
    "sea_level": 1019,
    "grnd_level": 1009
  },
  "visibility": 10000,
  "wind": {
    "speed": 2.06,
    "deg": 350
  },
  "clouds": {
    "all": 0
  },
  "dt": 1771094003,
  "sys": {
    "type": 1,
    "id": 6550,
    "country": "FR",
    "sunrise": 1771052463,
    "sunset": 1771088925
  },
  "timezone": 3600,
  "id": 2988507,
  "name": "Paris",
  "cod": 200,
  "_last_updated_utc": "2026-02-14T18:41:45.537Z"
}