{
  "coord": {
    "lon": 2.3488,
    "lat": 48.8534
  },
  "weather": [
    {
      "id": 803,
      "main": "Clouds",
      "description": "broken clouds",
      "icon": "04d"
    }
  ],
  "base": "stations",
  "main": {
    "temp": 9.66,
    "feels_like": 6.75,
    "temp_min": 8.97,
    "temp_max": 10.28,
    "pressure": 1023,
    "humidity": 66,
    "sea_level": 1023,
    "grnd_level": 1013
  },
  "visibility": 10000,
  "wind": {
    "speed": 6.17,
    "deg": 340
  },
  "clouds": {
    "all": 75
  },
  "dt": 1774693539,
  "sys": {
    "type": 2,
    "id": 2012208,
    "country": "FR",
    "sunrise": 1774676220,
    "sunset": 1774721653
  },
  "timezone": 3600,
  "id": 2988507,
  "name": "Paris",
  "cod": 200,
  "_last_updated_utc": "2026-03-28T10:37:10.721Z"
}