{
  "coord": {
    "lon": 2.3488,
    "lat": 48.8534
  },
  "weather": [
    {
      "id": 741,
      "main": "Fog",
      "description": "fog",
      "icon": "50n"
    }
  ],
  "base": "stations",
  "main": {
    "temp": 6.52,
    "feels_like": 3.95,
    "temp_min": 5.59,
    "temp_max": 7.43,
    "pressure": 1026,
    "humidity": 98,
    "sea_level": 1026,
    "grnd_level": 1016
  },
  "visibility": 450,
  "wind": {
    "speed": 3.6,
    "deg": 130
  },
  "clouds": {
    "all": 100
  },
  "dt": 1765694759,
  "sys": {
    "type": 2,
    "id": 2012208,
    "country": "FR",
    "sunrise": 1765697805,
    "sunset": 1765727641
  },
  "timezone": 3600,
  "id": 2988507,
  "name": "Paris",
  "cod": 200,
  "_last_updated_utc": "2025-12-14T06:55:51.739Z"
}